uci_phonotactic_calculator/__init__.py
uci_phonotactic_calculator/py.typed
uci_phonotactic_calculator/cli/__init__.py
uci_phonotactic_calculator/cli/demo_data.py
uci_phonotactic_calculator/cli/extensions.py
uci_phonotactic_calculator/cli/formatter.py
uci_phonotactic_calculator/cli/legacy.py
uci_phonotactic_calculator/cli/main.py
uci_phonotactic_calculator/cli/parser.py
uci_phonotactic_calculator/cli/utils.py
uci_phonotactic_calculator/core/__init__.py
uci_phonotactic_calculator/core/config.py
uci_phonotactic_calculator/core/corpus.py
uci_phonotactic_calculator/core/filter_aliases.py
uci_phonotactic_calculator/core/header_schema.py
uci_phonotactic_calculator/core/header_utils.py
uci_phonotactic_calculator/core/probability.py
uci_phonotactic_calculator/core/registries.py
uci_phonotactic_calculator/core/variants.py
uci_phonotactic_calculator/data/corpus_descriptions.txt
uci_phonotactic_calculator/data/english.csv
uci_phonotactic_calculator/data/english_freq.csv
uci_phonotactic_calculator/data/english_needle.csv
uci_phonotactic_calculator/data/english_onsets.csv
uci_phonotactic_calculator/data/finnish.csv
uci_phonotactic_calculator/data/french.csv
uci_phonotactic_calculator/data/polish_onsets.csv
uci_phonotactic_calculator/data/samoan.csv
uci_phonotactic_calculator/data/spanish_stress.csv
uci_phonotactic_calculator/data/turkish.csv
uci_phonotactic_calculator/data/sample_test_data/albright_cleaned_test_data.csv
uci_phonotactic_calculator/data/sample_test_data/cleaned_polish_test_data.csv
uci_phonotactic_calculator/data/sample_test_data/daland_test_data.csv
uci_phonotactic_calculator/data/sample_test_data/english_test_data.csv
uci_phonotactic_calculator/data/sample_test_data/needle_test_data.csv
uci_phonotactic_calculator/data/sample_test_data/scholes_cleaned_test_data.csv
uci_phonotactic_calculator/data/sample_test_data/spanish_test_data_no_stress.csv
uci_phonotactic_calculator/data/sample_test_data/white_hayes_cleaned_fixed_test_data.csv
uci_phonotactic_calculator-1.0.1.dist-info/licenses/LICENSE
uci_phonotactic_calculator-1.0.1.dist-info/METADATA
uci_phonotactic_calculator-1.0.1.dist-info/WHEEL
uci_phonotactic_calculator-1.0.1.dist-info/entry_points.txt
uci_phonotactic_calculator-1.0.1.dist-info/top_level.txt
uci_phonotactic_calculator-1.0.1.dist-info/RECORD
