Metadata-Version: 2.4
Name: uci-phonotactic-calculator
Version: 1.0.1
Summary: A toolkit for phonotactic probability calculation and analysis.
Author-email: Connor Mayer <cjmayer@uci.edu>, Austin Wagner <austinwagner@msn.com>
License:                     GNU GENERAL PUBLIC LICENSE
Project-URL: Homepage, https://github.com/connormayer/uci_phonotactic_calculator
Project-URL: Documentation, https://github.com/connormayer/uci_phonotactic_calculator#readme
Project-URL: Issues, https://github.com/connormayer/uci_phonotactic_calculator/issues
Requires-Python: >=3.8
License-File: LICENSE
Requires-Dist: rich>=13.7
Requires-Dist: numpy>=1.21
Requires-Dist: pandas>=1.3.0
Provides-Extra: gradio
Requires-Dist: setuptools; extra == "gradio"
Requires-Dist: gradio>=4.0.0; extra == "gradio"
Provides-Extra: django
Requires-Dist: django>=4.2.0; extra == "django"
Requires-Dist: django-crispy-forms>=2.0.0; extra == "django"
Requires-Dist: django-stubs>=5.0.0; extra == "django"
Requires-Dist: django-latexify>=0.3; extra == "django"
Requires-Dist: django-crontab>=0.7; extra == "django"
Provides-Extra: dev
Requires-Dist: pytest>=8.0.0; extra == "dev"
Requires-Dist: pytest-cov>=4.0.0; extra == "dev"
Requires-Dist: ruff>=0.4.0; extra == "dev"
Requires-Dist: mypy>=1.10.0; extra == "dev"
Requires-Dist: build>=0.10.0; extra == "dev"
Dynamic: license-file
